mcp_server_deepresearch_liu/__init__.py
mcp_server_deepresearch_liu/__main__.py
mcp_server_deepresearch_liu/server.py
mcp_server_deepresearch_liu-0.1.4.dist-info/METADATA
mcp_server_deepresearch_liu-0.1.4.dist-info/WHEEL
mcp_server_deepresearch_liu-0.1.4.dist-info/entry_points.txt
mcp_server_deepresearch_liu-0.1.4.dist-info/top_level.txt
mcp_server_deepresearch_liu-0.1.4.dist-info/RECORD
